tap_rest_api_msdk/__init__.py
tap_rest_api_msdk/auth.py
tap_rest_api_msdk/client.py
tap_rest_api_msdk/pagination.py
tap_rest_api_msdk/streams.py
tap_rest_api_msdk/tap.py
tap_rest_api_msdk/utils.py
tap_rest_api_msdk-1.4.2.dist-info/METADATA
tap_rest_api_msdk-1.4.2.dist-info/LICENSE
tap_rest_api_msdk-1.4.2.dist-info/entry_points.txt
tap_rest_api_msdk-1.4.2.dist-info/WHEEL
tap_rest_api_msdk-1.4.2.dist-info/RECORD
