Metadata-Version: 2.1
Name: tap-rest-api-msdk
Version: 1.4.2
Summary: `tap-rest-api-msdk` is a Singer tap for REST APIs, built with the Meltano SDK for Singer Taps.
Home-page: https://github.com/Widen/tap-rest-api-msdk
License: Apache 2.0
Keywords: ELT,rest-api-msdk,Meltano,Singer,REST,API,tap
Author: Josh Lloyd
Requires-Python: >=3.8
Classifier: License :: Other/Proprietary License
Classifier: Programming Language :: Python :: 3
Classifier: Programming Language :: Python :: 3.8
Classifier: Programming Language :: Python :: 3.9
Classifier: Programming Language :: Python :: 3.10
Classifier: Programming Language :: Python :: 3.11
Requires-Dist: atomicwrites (>=1.4.0,<2.0.0)
Requires-Dist: boto3 (>=1.26.156,<2.0.0)
Requires-Dist: genson (>=1.2.2,<2.0.0)
Requires-Dist: requests (>=2.25.1,<3.0.0)
Requires-Dist: requests-aws4auth (>=1.2.3,<2.0.0)
Requires-Dist: singer-sdk (>=0.40.0,<0.41.0) ; python_version < "4"
Project-URL: Repository, https://github.com/Widen/tap-rest-api-msdk
